AUTHORS
LICENSE
MANIFEST.in
README.rst
setup.py
chinapostairmail/__init__.py
track_china_post_air_mail.egg-info/PKG-INFO
track_china_post_air_mail.egg-info/SOURCES.txt
track_china_post_air_mail.egg-info/dependency_links.txt
track_china_post_air_mail.egg-info/entry_points.txt
track_china_post_air_mail.egg-info/not-zip-safe
track_china_post_air_mail.egg-info/requires.txt
track_china_post_air_mail.egg-info/top_level.txt