Metadata-Version: 1.1
Name: track-china-post-air-mail
Version: 1.0
Summary: ChinaPost / AirMail tracking GUI
Home-page: http://github.com/gotlium/track-china-post-air-mail
Author: GoTLiuM InSPiRIT
Author-email: gotlium@gmail.com
License: UNKNOWN
Platform: UNKNOWN
Classifier: Development Status :: 4 - Beta
Classifier: Environment :: Web Environment
Classifier: Intended Audience :: Developers
Classifier: License :: OSI Approved :: GNU General Public License (GPL)
Classifier: Operating System :: POSIX
Classifier: Programming Language :: Python
